Metadata-Version: 2.1
Name: botty-mcbotface
Version: 1.5.3
Summary: General purpose Slack-bot with personality
Home-page: https://github.com/ColumbiaSC-Tech/botty_mcbotface
Author: Danny Hinshaw
Author-email: danny@nulleffort.com
License: MIT
Keywords: slack bot slackbot botty_mcbotface botty gonzobot
Platform: UNKNOWN
Classifier: Development Status :: 3 - Alpha
Classifier: Intended Audience :: Developers
Classifier: License :: OSI Approved :: MIT License
Classifier: Programming Language :: Python :: 3.7
Requires-Python: >=3.7
Requires-Dist: apscheduler
Requires-Dist: arrow
Requires-Dist: bs4
Requires-Dist: certifi
Requires-Dist: cchardet
Requires-Dist: google-api-python-client
Requires-Dist: google-auth
Requires-Dist: idna
Requires-Dist: lxml
Requires-Dist: nose
Requires-Dist: python-dateutil
Requires-Dist: pytz
Requires-Dist: requests
Requires-Dist: slackbot
Requires-Dist: slacker
Requires-Dist: sqlalchemy
Requires-Dist: tzlocal
Requires-Dist: urllib3
Requires-Dist: websocket-client
